{"nodes": [], "edges": [{"source": "component_structure_defterim", "target": "component_structure_use_journal_entries", "relation": "calls", "confidence": "EXTRACTED", "confidence_score": 1.0, "source_file": "QUICK_START_GUIDE.md", "source_location": null, "weight": 1.0}, {"source": "component_structure_defterim", "target": "component_structure_journal_context", "relation": "references", "confidence": "EXTRACTED", "confidence_score": 1.0, "source_file": "QUICK_START_GUIDE.md", "source_location": null, "weight": 1.0}], "hyperedges": []}