{"nodes": [{"id": "d_film_ele\u015ftirmen_backend_movie_pool_expander_py", "label": "movie_pool_expander.py", "file_type": "code", "source_file": "D:\\film ele\u015ftirmen\\backend\\movie_pool_expander.py", "source_location": "L1"}, {"id": "backend_movie_pool_expander_reset_state", "label": "_reset_state()", "file_type": "code", "source_file": "D:\\film ele\u015ftirmen\\backend\\movie_pool_expander.py", "source_location": "L47"}, {"id": "backend_movie_pool_expander_build_response", "label": "_build_response()", "file_type": "code", "source_file": "D:\\film ele\u015ftirmen\\backend\\movie_pool_expander.py", "source_location": "L57"}, {"id": "backend_movie_pool_expander_process_and_save", "label": "_process_and_save()", "file_type": "code", "source_file": "D:\\film ele\u015ftirmen\\backend\\movie_pool_expander.py", "source_location": "L72"}, {"id": "str", "label": "str", "file_type": "code", "source_file": "D:\\film ele\u015ftirmen\\backend\\movie_pool_expander.py", "source_location": "L72"}, {"id": "int", "label": "int", "file_type": "code", "source_file": "D:\\film ele\u015ftirmen\\backend\\movie_pool_expander.py", "source_location": "L72"}, {"id": "backend_movie_pool_expander_fetch_page", "label": "_fetch_page()", "file_type": "code", "source_file": "D:\\film ele\u015ftirmen\\backend\\movie_pool_expander.py", "source_location": "L117"}, {"id": "backend_movie_pool_expander_expand_popular", "label": "_expand_popular()", "file_type": "code", "source_file": "D:\\film ele\u015ftirmen\\backend\\movie_pool_expander.py", "source_location": "L135"}, {"id": "backend_movie_pool_expander_expand_top_rated", "label": "_expand_top_rated()", "file_type": "code", "source_file": "D:\\film ele\u015ftirmen\\backend\\movie_pool_expander.py", "source_location": "L155"}, {"id": "backend_movie_pool_expander_expand_by_year", "label": "_expand_by_year()", "file_type": "code", "source_file": "D:\\film ele\u015ftirmen\\backend\\movie_pool_expander.py", "source_location": "L181"}, {"id": "backend_movie_pool_expander_expand_by_genre", "label": "_expand_by_genre()", "file_type": "code", "source_file": "D:\\film ele\u015ftirmen\\backend\\movie_pool_expander.py", "source_location": "L205"}, {"id": "backend_movie_pool_expander_expand_by_language", "label": "_expand_by_language()", "file_type": "code", "source_file": "D:\\film ele\u015ftirmen\\backend\\movie_pool_expander.py", "source_location": "L226"}, {"id": "backend_movie_pool_expander_expand_similar_and_recs", "label": "_expand_similar_and_recs()", "file_type": "code", "source_file": "D:\\film ele\u015ftirmen\\backend\\movie_pool_expander.py", "source_location": "L253"}, {"id": "backend_movie_pool_expander_expand_mood_pool", "label": "expand_mood_pool()", "file_type": "code", "source_file": "D:\\film ele\u015ftirmen\\backend\\movie_pool_expander.py", "source_location": "L283"}, {"id": "backend_movie_pool_expander_expand_all_moods", "label": "expand_all_moods()", "file_type": "code", "source_file": "D:\\film ele\u015ftirmen\\backend\\movie_pool_expander.py", "source_location": "L302"}, {"id": "backend_movie_pool_expander_rationale_1", "label": "Movie Pool Expander v3 \u2014 Professional movie pool expansion system. Target: 15,00", "file_type": "rationale", "source_file": "D:\\film ele\u015ftirmen\\backend\\movie_pool_expander.py", "source_location": "L1"}, {"id": "backend_movie_pool_expander_rationale_73", "label": "Calculate mood score, save if above threshold. Returns 0/1.", "file_type": "rationale", "source_file": "D:\\film ele\u015ftirmen\\backend\\movie_pool_expander.py", "source_location": "L73"}, {"id": "backend_movie_pool_expander_rationale_118", "label": "Fetch one discover page, process all movies.", "file_type": "rationale", "source_file": "D:\\film ele\u015ftirmen\\backend\\movie_pool_expander.py", "source_location": "L118"}, {"id": "backend_movie_pool_expander_rationale_284", "label": "Expand a single mood using all sources.", "file_type": "rationale", "source_file": "D:\\film ele\u015ftirmen\\backend\\movie_pool_expander.py", "source_location": "L284"}, {"id": "backend_movie_pool_expander_rationale_303", "label": "Expand all moods (or one if mood_filter is set).", "file_type": "rationale", "source_file": "D:\\film ele\u015ftirmen\\backend\\movie_pool_expander.py", "source_location": "L303"}], "edges": [{"source": "d_film_ele\u015ftirmen_backend_movie_pool_expander_py", "target": "asyncio", "relation": "imports", "context": "import", "confidence": "EXTRACTED", "source_file": "D:\\film ele\u015ftirmen\\backend\\movie_pool_expander.py", "source_location": "L16", "weight": 1.0}, {"source": "d_film_ele\u015ftirmen_backend_movie_pool_expander_py", "target": "logging", "relation": "imports", "context": "import", "confidence": "EXTRACTED", "source_file": "D:\\film ele\u015ftirmen\\backend\\movie_pool_expander.py", "source_location": "L16", "weight": 1.0}, {"source": "d_film_ele\u015ftirmen_backend_movie_pool_expander_py", "target": "random", "relation": "imports", "context": "import", "confidence": "EXTRACTED", "source_file": "D:\\film ele\u015ftirmen\\backend\\movie_pool_expander.py", "source_location": "L16", "weight": 1.0}, {"source": "d_film_ele\u015ftirmen_backend_movie_pool_expander_py", "target": "httpx", "relation": "imports", "context": "import", "confidence": "EXTRACTED", "source_file": "D:\\film ele\u015ftirmen\\backend\\movie_pool_expander.py", "source_location": "L16", "weight": 1.0}, {"source": "d_film_ele\u015ftirmen_backend_movie_pool_expander_py", "target": "time", "relation": "imports", "context": "import", "confidence": "EXTRACTED", "source_file": "D:\\film ele\u015ftirmen\\backend\\movie_pool_expander.py", "source_location": "L16", "weight": 1.0}, {"source": "d_film_ele\u015ftirmen_backend_movie_pool_expander_py", "target": "json", "relation": "imports", "context": "import", "confidence": "EXTRACTED", "source_file": "D:\\film ele\u015ftirmen\\backend\\movie_pool_expander.py", "source_location": "L16", "weight": 1.0}, {"source": "d_film_ele\u015ftirmen_backend_movie_pool_expander_py", "target": "datetime", "relation": "imports_from", "context": "import", "confidence": "EXTRACTED", "source_file": "D:\\film ele\u015ftirmen\\backend\\movie_pool_expander.py", "source_location": "L17", "weight": 1.0}, {"source": "d_film_ele\u015ftirmen_backend_movie_pool_expander_py", "target": "backend_mood_scoring", "relation": "imports_from", "context": "import", "confidence": "EXTRACTED", "source_file": "D:\\film ele\u015ftirmen\\backend\\movie_pool_expander.py", "source_location": "L18", "weight": 1.0}, {"source": "d_film_ele\u015ftirmen_backend_movie_pool_expander_py", "target": "backend_database", "relation": "imports_from", "context": "import", "confidence": "EXTRACTED", "source_file": "D:\\film ele\u015ftirmen\\backend\\movie_pool_expander.py", "source_location": "L19", "weight": 1.0}, {"source": "d_film_ele\u015ftirmen_backend_movie_pool_expander_py", "target": "backend_services_tmdb_service", "relation": "imports_from", "context": "import", "confidence": "EXTRACTED", "source_file": "D:\\film ele\u015ftirmen\\backend\\movie_pool_expander.py", "source_location": "L20", "weight": 1.0}, {"source": "d_film_ele\u015ftirmen_backend_movie_pool_expander_py", "target": "backend_movie_pool_expander_reset_state", "relation": "contains", "confidence": "EXTRACTED", "source_file": "D:\\film ele\u015ftirmen\\backend\\movie_pool_expander.py", "source_location": "L47", "weight": 1.0}, {"source": "d_film_ele\u015ftirmen_backend_movie_pool_expander_py", "target": "backend_movie_pool_expander_build_response", "relation": "contains", "confidence": "EXTRACTED", "source_file": "D:\\film ele\u015ftirmen\\backend\\movie_pool_expander.py", "source_location": "L57", "weight": 1.0}, {"source": "d_film_ele\u015ftirmen_backend_movie_pool_expander_py", "target": "backend_movie_pool_expander_process_and_save", "relation": "contains", "confidence": "EXTRACTED", "source_file": "D:\\film ele\u015ftirmen\\backend\\movie_pool_expander.py", "source_location": "L72", "weight": 1.0}, {"source": "backend_movie_pool_expander_process_and_save", "target": "str", "relation": "references", "context": "parameter_type", "confidence": "EXTRACTED", "source_file": "D:\\film ele\u015ftirmen\\backend\\movie_pool_expander.py", "source_location": "L72", "weight": 1.0}, {"source": "backend_movie_pool_expander_process_and_save", "target": "int", "relation": "references", "context": "return_type", "confidence": "EXTRACTED", "source_file": "D:\\film ele\u015ftirmen\\backend\\movie_pool_expander.py", "source_location": "L72", "weight": 1.0}, {"source": "d_film_ele\u015ftirmen_backend_movie_pool_expander_py", "target": "backend_movie_pool_expander_fetch_page", "relation": "contains", "confidence": "EXTRACTED", "source_file": "D:\\film ele\u015ftirmen\\backend\\movie_pool_expander.py", "source_location": "L117", "weight": 1.0}, {"source": "backend_movie_pool_expander_fetch_page", "target": "str", "relation": "references", "context": "parameter_type", "confidence": "EXTRACTED", "source_file": "D:\\film ele\u015ftirmen\\backend\\movie_pool_expander.py", "source_location": "L117", "weight": 1.0}, {"source": "backend_movie_pool_expander_fetch_page", "target": "str", "relation": "references", "context": "parameter_type", "confidence": "EXTRACTED", "source_file": "D:\\film ele\u015ftirmen\\backend\\movie_pool_expander.py", "source_location": "L117", "weight": 1.0}, {"source": "backend_movie_pool_expander_fetch_page", "target": "int", "relation": "references", "context": "parameter_type", "confidence": "EXTRACTED", "source_file": "D:\\film ele\u015ftirmen\\backend\\movie_pool_expander.py", "source_location": "L117", "weight": 1.0}, {"source": "backend_movie_pool_expander_fetch_page", "target": "int", "relation": "references", "context": "return_type", "confidence": "EXTRACTED", "source_file": "D:\\film ele\u015ftirmen\\backend\\movie_pool_expander.py", "source_location": "L117", "weight": 1.0}, {"source": "d_film_ele\u015ftirmen_backend_movie_pool_expander_py", "target": "backend_movie_pool_expander_expand_popular", "relation": "contains", "confidence": "EXTRACTED", "source_file": "D:\\film ele\u015ftirmen\\backend\\movie_pool_expander.py", "source_location": "L135", "weight": 1.0}, {"source": "backend_movie_pool_expander_expand_popular", "target": "str", "relation": "references", "context": "parameter_type", "confidence": "EXTRACTED", "source_file": "D:\\film ele\u015ftirmen\\backend\\movie_pool_expander.py", "source_location": "L135", "weight": 1.0}, {"source": "backend_movie_pool_expander_expand_popular", "target": "int", "relation": "references", "context": "return_type", "confidence": "EXTRACTED", "source_file": "D:\\film ele\u015ftirmen\\backend\\movie_pool_expander.py", "source_location": "L135", "weight": 1.0}, {"source": "d_film_ele\u015ftirmen_backend_movie_pool_expander_py", "target": "backend_movie_pool_expander_expand_top_rated", "relation": "contains", "confidence": "EXTRACTED", "source_file": "D:\\film ele\u015ftirmen\\backend\\movie_pool_expander.py", "source_location": "L155", "weight": 1.0}, {"source": "backend_movie_pool_expander_expand_top_rated", "target": "str", "relation": "references", "context": "parameter_type", "confidence": "EXTRACTED", "source_file": "D:\\film ele\u015ftirmen\\backend\\movie_pool_expander.py", "source_location": "L155", "weight": 1.0}, {"source": "backend_movie_pool_expander_expand_top_rated", "target": "int", "relation": "references", "context": "return_type", "confidence": "EXTRACTED", "source_file": "D:\\film ele\u015ftirmen\\backend\\movie_pool_expander.py", "source_location": "L155", "weight": 1.0}, {"source": "d_film_ele\u015ftirmen_backend_movie_pool_expander_py", "target": "backend_movie_pool_expander_expand_by_year", "relation": "contains", "confidence": "EXTRACTED", "source_file": "D:\\film ele\u015ftirmen\\backend\\movie_pool_expander.py", "source_location": "L181", "weight": 1.0}, {"source": "backend_movie_pool_expander_expand_by_year", "target": "str", "relation": "references", "context": "parameter_type", "confidence": "EXTRACTED", "source_file": "D:\\film ele\u015ftirmen\\backend\\movie_pool_expander.py", "source_location": "L181", "weight": 1.0}, {"source": "backend_movie_pool_expander_expand_by_year", "target": "int", "relation": "references", "context": "return_type", "confidence": "EXTRACTED", "source_file": "D:\\film ele\u015ftirmen\\backend\\movie_pool_expander.py", "source_location": "L181", "weight": 1.0}, {"source": "d_film_ele\u015ftirmen_backend_movie_pool_expander_py", "target": "backend_movie_pool_expander_expand_by_genre", "relation": "contains", "confidence": "EXTRACTED", "source_file": "D:\\film ele\u015ftirmen\\backend\\movie_pool_expander.py", "source_location": "L205", "weight": 1.0}, {"source": "backend_movie_pool_expander_expand_by_genre", "target": "str", "relation": "references", "context": "parameter_type", "confidence": "EXTRACTED", "source_file": "D:\\film ele\u015ftirmen\\backend\\movie_pool_expander.py", "source_location": "L205", "weight": 1.0}, {"source": "backend_movie_pool_expander_expand_by_genre", "target": "int", "relation": "references", "context": "return_type", "confidence": "EXTRACTED", "source_file": "D:\\film ele\u015ftirmen\\backend\\movie_pool_expander.py", "source_location": "L205", "weight": 1.0}, {"source": "d_film_ele\u015ftirmen_backend_movie_pool_expander_py", "target": "backend_movie_pool_expander_expand_by_language", "relation": "contains", "confidence": "EXTRACTED", "source_file": "D:\\film ele\u015ftirmen\\backend\\movie_pool_expander.py", "source_location": "L226", "weight": 1.0}, {"source": "backend_movie_pool_expander_expand_by_language", "target": "str", "relation": "references", "context": "parameter_type", "confidence": "EXTRACTED", "source_file": "D:\\film ele\u015ftirmen\\backend\\movie_pool_expander.py", "source_location": "L226", "weight": 1.0}, {"source": "backend_movie_pool_expander_expand_by_language", "target": "int", "relation": "references", "context": "return_type", "confidence": "EXTRACTED", "source_file": "D:\\film ele\u015ftirmen\\backend\\movie_pool_expander.py", "source_location": "L226", "weight": 1.0}, {"source": "d_film_ele\u015ftirmen_backend_movie_pool_expander_py", "target": "backend_movie_pool_expander_expand_similar_and_recs", "relation": "contains", "confidence": "EXTRACTED", "source_file": "D:\\film ele\u015ftirmen\\backend\\movie_pool_expander.py", "source_location": "L253", "weight": 1.0}, {"source": "backend_movie_pool_expander_expand_similar_and_recs", "target": "str", "relation": "references", "context": "parameter_type", "confidence": "EXTRACTED", "source_file": "D:\\film ele\u015ftirmen\\backend\\movie_pool_expander.py", "source_location": "L253", "weight": 1.0}, {"source": "backend_movie_pool_expander_expand_similar_and_recs", "target": "int", "relation": "references", "context": "return_type", "confidence": "EXTRACTED", "source_file": "D:\\film ele\u015ftirmen\\backend\\movie_pool_expander.py", "source_location": "L253", "weight": 1.0}, {"source": "d_film_ele\u015ftirmen_backend_movie_pool_expander_py", "target": "backend_movie_pool_expander_expand_mood_pool", "relation": "contains", "confidence": "EXTRACTED", "source_file": "D:\\film ele\u015ftirmen\\backend\\movie_pool_expander.py", "source_location": "L283", "weight": 1.0}, {"source": "backend_movie_pool_expander_expand_mood_pool", "target": "str", "relation": "references", "context": "parameter_type", "confidence": "EXTRACTED", "source_file": "D:\\film ele\u015ftirmen\\backend\\movie_pool_expander.py", "source_location": "L283", "weight": 1.0}, {"source": "d_film_ele\u015ftirmen_backend_movie_pool_expander_py", "target": "backend_movie_pool_expander_expand_all_moods", "relation": "contains", "confidence": "EXTRACTED", "source_file": "D:\\film ele\u015ftirmen\\backend\\movie_pool_expander.py", "source_location": "L302", "weight": 1.0}, {"source": "backend_movie_pool_expander_expand_all_moods", "target": "str", "relation": "references", "context": "parameter_type", "confidence": "EXTRACTED", "source_file": "D:\\film ele\u015ftirmen\\backend\\movie_pool_expander.py", "source_location": "L302", "weight": 1.0}, {"source": "backend_movie_pool_expander_fetch_page", "target": "backend_movie_pool_expander_process_and_save", "relation": "calls", "context": "call", "confidence": "EXTRACTED", "source_file": "D:\\film ele\u015ftirmen\\backend\\movie_pool_expander.py", "source_location": "L125", "weight": 1.0}, {"source": "backend_movie_pool_expander_fetch_page", "target": "str", "relation": "calls", "context": "call", "confidence": "EXTRACTED", "source_file": "D:\\film ele\u015ftirmen\\backend\\movie_pool_expander.py", "source_location": "L130", "weight": 1.0}, {"source": "backend_movie_pool_expander_expand_popular", "target": "backend_movie_pool_expander_process_and_save", "relation": "calls", "context": "call", "confidence": "EXTRACTED", "source_file": "D:\\film ele\u015ftirmen\\backend\\movie_pool_expander.py", "source_location": "L144", "weight": 1.0}, {"source": "backend_movie_pool_expander_expand_popular", "target": "str", "relation": "calls", "context": "call", "confidence": "EXTRACTED", "source_file": "D:\\film ele\u015ftirmen\\backend\\movie_pool_expander.py", "source_location": "L148", "weight": 1.0}, {"source": "backend_movie_pool_expander_expand_top_rated", "target": "backend_movie_pool_expander_process_and_save", "relation": "calls", "context": "call", "confidence": "EXTRACTED", "source_file": "D:\\film ele\u015ftirmen\\backend\\movie_pool_expander.py", "source_location": "L170", "weight": 1.0}, {"source": "backend_movie_pool_expander_expand_top_rated", "target": "str", "relation": "calls", "context": "call", "confidence": "EXTRACTED", "source_file": "D:\\film ele\u015ftirmen\\backend\\movie_pool_expander.py", "source_location": "L174", "weight": 1.0}, {"source": "backend_movie_pool_expander_expand_by_year", "target": "backend_movie_pool_expander_fetch_page", "relation": "calls", "context": "call", "confidence": "EXTRACTED", "source_file": "D:\\film ele\u015ftirmen\\backend\\movie_pool_expander.py", "source_location": "L194", "weight": 1.0}, {"source": "backend_movie_pool_expander_expand_by_year", "target": "str", "relation": "calls", "context": "call", "confidence": "EXTRACTED", "source_file": "D:\\film ele\u015ftirmen\\backend\\movie_pool_expander.py", "source_location": "L199", "weight": 1.0}, {"source": "backend_movie_pool_expander_expand_by_genre", "target": "backend_movie_pool_expander_fetch_page", "relation": "calls", "context": "call", "confidence": "EXTRACTED", "source_file": "D:\\film ele\u015ftirmen\\backend\\movie_pool_expander.py", "source_location": "L217", "weight": 1.0}, {"source": "backend_movie_pool_expander_expand_by_genre", "target": "str", "relation": "calls", "context": "call", "confidence": "EXTRACTED", "source_file": "D:\\film ele\u015ftirmen\\backend\\movie_pool_expander.py", "source_location": "L220", "weight": 1.0}, {"source": "backend_movie_pool_expander_expand_by_language", "target": "backend_movie_pool_expander_fetch_page", "relation": "calls", "context": "call", "confidence": "EXTRACTED", "source_file": "D:\\film ele\u015ftirmen\\backend\\movie_pool_expander.py", "source_location": "L244", "weight": 1.0}, {"source": "backend_movie_pool_expander_expand_by_language", "target": "str", "relation": "calls", "context": "call", "confidence": "EXTRACTED", "source_file": "D:\\film ele\u015ftirmen\\backend\\movie_pool_expander.py", "source_location": "L247", "weight": 1.0}, {"source": "backend_movie_pool_expander_expand_similar_and_recs", "target": "backend_movie_pool_expander_process_and_save", "relation": "calls", "context": "call", "confidence": "EXTRACTED", "source_file": "D:\\film ele\u015ftirmen\\backend\\movie_pool_expander.py", "source_location": "L272", "weight": 1.0}, {"source": "backend_movie_pool_expander_expand_similar_and_recs", "target": "str", "relation": "calls", "context": "call", "confidence": "EXTRACTED", "source_file": "D:\\film ele\u015ftirmen\\backend\\movie_pool_expander.py", "source_location": "L277", "weight": 1.0}, {"source": "backend_movie_pool_expander_expand_mood_pool", "target": "backend_movie_pool_expander_reset_state", "relation": "calls", "context": "call", "confidence": "EXTRACTED", "source_file": "D:\\film ele\u015ftirmen\\backend\\movie_pool_expander.py", "source_location": "L288", "weight": 1.0}, {"source": "backend_movie_pool_expander_expand_mood_pool", "target": "backend_movie_pool_expander_expand_popular", "relation": "calls", "context": "call", "confidence": "EXTRACTED", "source_file": "D:\\film ele\u015ftirmen\\backend\\movie_pool_expander.py", "source_location": "L291", "weight": 1.0}, {"source": "backend_movie_pool_expander_expand_mood_pool", "target": "backend_movie_pool_expander_expand_top_rated", "relation": "calls", "context": "call", "confidence": "EXTRACTED", "source_file": "D:\\film ele\u015ftirmen\\backend\\movie_pool_expander.py", "source_location": "L292", "weight": 1.0}, {"source": "backend_movie_pool_expander_expand_mood_pool", "target": "backend_movie_pool_expander_expand_by_year", "relation": "calls", "context": "call", "confidence": "EXTRACTED", "source_file": "D:\\film ele\u015ftirmen\\backend\\movie_pool_expander.py", "source_location": "L293", "weight": 1.0}, {"source": "backend_movie_pool_expander_expand_mood_pool", "target": "backend_movie_pool_expander_expand_by_genre", "relation": "calls", "context": "call", "confidence": "EXTRACTED", "source_file": "D:\\film ele\u015ftirmen\\backend\\movie_pool_expander.py", "source_location": "L294", "weight": 1.0}, {"source": "backend_movie_pool_expander_expand_mood_pool", "target": "backend_movie_pool_expander_expand_by_language", "relation": "calls", "context": "call", "confidence": "EXTRACTED", "source_file": "D:\\film ele\u015ftirmen\\backend\\movie_pool_expander.py", "source_location": "L295", "weight": 1.0}, {"source": "backend_movie_pool_expander_expand_mood_pool", "target": "backend_movie_pool_expander_expand_similar_and_recs", "relation": "calls", "context": "call", "confidence": "EXTRACTED", "source_file": "D:\\film ele\u015ftirmen\\backend\\movie_pool_expander.py", "source_location": "L296", "weight": 1.0}, {"source": "backend_movie_pool_expander_expand_mood_pool", "target": "backend_movie_pool_expander_build_response", "relation": "calls", "context": "call", "confidence": "EXTRACTED", "source_file": "D:\\film ele\u015ftirmen\\backend\\movie_pool_expander.py", "source_location": "L299", "weight": 1.0}, {"source": "backend_movie_pool_expander_expand_all_moods", "target": "backend_movie_pool_expander_expand_mood_pool", "relation": "calls", "context": "call", "confidence": "EXTRACTED", "source_file": "D:\\film ele\u015ftirmen\\backend\\movie_pool_expander.py", "source_location": "L305", "weight": 1.0}, {"source": "backend_movie_pool_expander_expand_all_moods", "target": "str", "relation": "calls", "context": "call", "confidence": "EXTRACTED", "source_file": "D:\\film ele\u015ftirmen\\backend\\movie_pool_expander.py", "source_location": "L325", "weight": 1.0}, {"source": "backend_movie_pool_expander_rationale_1", "target": "d_film_ele\u015ftirmen_backend_movie_pool_expander_py", "relation": "rationale_for", "confidence": "EXTRACTED", "source_file": "D:\\film ele\u015ftirmen\\backend\\movie_pool_expander.py", "source_location": "L1", "weight": 1.0}, {"source": "backend_movie_pool_expander_rationale_73", "target": "backend_movie_pool_expander_process_and_save", "relation": "rationale_for", "confidence": "EXTRACTED", "source_file": "D:\\film ele\u015ftirmen\\backend\\movie_pool_expander.py", "source_location": "L73", "weight": 1.0}, {"source": "backend_movie_pool_expander_rationale_118", "target": "backend_movie_pool_expander_fetch_page", "relation": "rationale_for", "confidence": "EXTRACTED", "source_file": "D:\\film ele\u015ftirmen\\backend\\movie_pool_expander.py", "source_location": "L118", "weight": 1.0}, {"source": "backend_movie_pool_expander_rationale_284", "target": "backend_movie_pool_expander_expand_mood_pool", "relation": "rationale_for", "confidence": "EXTRACTED", "source_file": "D:\\film ele\u015ftirmen\\backend\\movie_pool_expander.py", "source_location": "L284", "weight": 1.0}, {"source": "backend_movie_pool_expander_rationale_303", "target": "backend_movie_pool_expander_expand_all_moods", "relation": "rationale_for", "confidence": "EXTRACTED", "source_file": "D:\\film ele\u015ftirmen\\backend\\movie_pool_expander.py", "source_location": "L303", "weight": 1.0}], "raw_calls": [{"caller_nid": "backend_movie_pool_expander_reset_state", "callee": "set", "is_member_call": false, "source_file": "D:\\film ele\u015ftirmen\\backend\\movie_pool_expander.py", "source_location": "L49"}, {"caller_nid": "backend_movie_pool_expander_build_response", "callee": "sum", "is_member_call": false, "source_file": "D:\\film ele\u015ftirmen\\backend\\movie_pool_expander.py", "source_location": "L65"}, {"caller_nid": "backend_movie_pool_expander_build_response", "callee": "values", "is_member_call": true, "source_file": "D:\\film ele\u015ftirmen\\backend\\movie_pool_expander.py", "source_location": "L65"}, {"caller_nid": "backend_movie_pool_expander_build_response", "callee": "dict", "is_member_call": false, "source_file": "D:\\film ele\u015ftirmen\\backend\\movie_pool_expander.py", "source_location": "L66"}, {"caller_nid": "backend_movie_pool_expander_process_and_save", "callee": "get", "is_member_call": true, "source_file": "D:\\film ele\u015ftirmen\\backend\\movie_pool_expander.py", "source_location": "L75"}, {"caller_nid": "backend_movie_pool_expander_process_and_save", "callee": "add", "is_member_call": true, "source_file": "D:\\film ele\u015ftirmen\\backend\\movie_pool_expander.py", "source_location": "L83"}, {"caller_nid": "backend_movie_pool_expander_process_and_save", "callee": "get", "is_member_call": true, "source_file": "D:\\film ele\u015ftirmen\\backend\\movie_pool_expander.py", "source_location": "L85"}, {"caller_nid": "backend_movie_pool_expander_process_and_save", "callee": "calculate_mood_scores", "is_member_call": false, "source_file": "D:\\film ele\u015ftirmen\\backend\\movie_pool_expander.py", "source_location": "L94"}, {"caller_nid": "backend_movie_pool_expander_process_and_save", "callee": "get", "is_member_call": true, "source_file": "D:\\film ele\u015ftirmen\\backend\\movie_pool_expander.py", "source_location": "L95"}, {"caller_nid": "backend_movie_pool_expander_process_and_save", "callee": "get", "is_member_call": true, "source_file": "D:\\film ele\u015ftirmen\\backend\\movie_pool_expander.py", "source_location": "L96"}, {"caller_nid": "backend_movie_pool_expander_process_and_save", "callee": "get", "is_member_call": true, "source_file": "D:\\film ele\u015ftirmen\\backend\\movie_pool_expander.py", "source_location": "L97"}, {"caller_nid": "backend_movie_pool_expander_process_and_save", "callee": "get", "is_member_call": true, "source_file": "D:\\film ele\u015ftirmen\\backend\\movie_pool_expander.py", "source_location": "L98"}, {"caller_nid": "backend_movie_pool_expander_process_and_save", "callee": "get", "is_member_call": true, "source_file": "D:\\film ele\u015ftirmen\\backend\\movie_pool_expander.py", "source_location": "L102"}, {"caller_nid": "backend_movie_pool_expander_process_and_save", "callee": "round", "is_member_call": false, "source_file": "D:\\film ele\u015ftirmen\\backend\\movie_pool_expander.py", "source_location": "L106"}, {"caller_nid": "backend_movie_pool_expander_process_and_save", "callee": "bulk_save_repository_movies", "is_member_call": true, "source_file": "D:\\film ele\u015ftirmen\\backend\\movie_pool_expander.py", "source_location": "L108"}, {"caller_nid": "backend_movie_pool_expander_process_and_save", "callee": "get", "is_member_call": true, "source_file": "D:\\film ele\u015ftirmen\\backend\\movie_pool_expander.py", "source_location": "L110"}, {"caller_nid": "backend_movie_pool_expander_process_and_save", "callee": "append", "is_member_call": true, "source_file": "D:\\film ele\u015ftirmen\\backend\\movie_pool_expander.py", "source_location": "L113"}, {"caller_nid": "backend_movie_pool_expander_fetch_page", "callee": "discover_movies", "is_member_call": true, "source_file": "D:\\film ele\u015ftirmen\\backend\\movie_pool_expander.py", "source_location": "L121"}, {"caller_nid": "backend_movie_pool_expander_fetch_page", "callee": "get", "is_member_call": true, "source_file": "D:\\film ele\u015ftirmen\\backend\\movie_pool_expander.py", "source_location": "L122"}, {"caller_nid": "backend_movie_pool_expander_fetch_page", "callee": "info", "is_member_call": true, "source_file": "D:\\film ele\u015ftirmen\\backend\\movie_pool_expander.py", "source_location": "L127"}, {"caller_nid": "backend_movie_pool_expander_fetch_page", "callee": "len", "is_member_call": false, "source_file": "D:\\film ele\u015ftirmen\\backend\\movie_pool_expander.py", "source_location": "L127"}, {"caller_nid": "backend_movie_pool_expander_fetch_page", "callee": "append", "is_member_call": true, "source_file": "D:\\film ele\u015ftirmen\\backend\\movie_pool_expander.py", "source_location": "L130"}, {"caller_nid": "backend_movie_pool_expander_expand_popular", "callee": "range", "is_member_call": false, "source_file": "D:\\film ele\u015ftirmen\\backend\\movie_pool_expander.py", "source_location": "L137"}, {"caller_nid": "backend_movie_pool_expander_expand_popular", "callee": "get_popular_movies", "is_member_call": true, "source_file": "D:\\film ele\u015ftirmen\\backend\\movie_pool_expander.py", "source_location": "L139"}, {"caller_nid": "backend_movie_pool_expander_expand_popular", "callee": "get", "is_member_call": true, "source_file": "D:\\film ele\u015ftirmen\\backend\\movie_pool_expander.py", "source_location": "L140"}, {"caller_nid": "backend_movie_pool_expander_expand_popular", "callee": "info", "is_member_call": true, "source_file": "D:\\film ele\u015ftirmen\\backend\\movie_pool_expander.py", "source_location": "L146"}, {"caller_nid": "backend_movie_pool_expander_expand_popular", "callee": "append", "is_member_call": true, "source_file": "D:\\film ele\u015ftirmen\\backend\\movie_pool_expander.py", "source_location": "L148"}, {"caller_nid": "backend_movie_pool_expander_expand_popular", "callee": "sleep", "is_member_call": true, "source_file": "D:\\film ele\u015ftirmen\\backend\\movie_pool_expander.py", "source_location": "L149"}, {"caller_nid": "backend_movie_pool_expander_expand_popular", "callee": "info", "is_member_call": true, "source_file": "D:\\film ele\u015ftirmen\\backend\\movie_pool_expander.py", "source_location": "L150"}, {"caller_nid": "backend_movie_pool_expander_expand_top_rated", "callee": "range", "is_member_call": false, "source_file": "D:\\film ele\u015ftirmen\\backend\\movie_pool_expander.py", "source_location": "L158"}, {"caller_nid": "backend_movie_pool_expander_expand_top_rated", "callee": "discover_movies", "is_member_call": true, "source_file": "D:\\film ele\u015ftirmen\\backend\\movie_pool_expander.py", "source_location": "L160"}, {"caller_nid": "backend_movie_pool_expander_expand_top_rated", "callee": "get", "is_member_call": true, "source_file": "D:\\film ele\u015ftirmen\\backend\\movie_pool_expander.py", "source_location": "L166"}, {"caller_nid": "backend_movie_pool_expander_expand_top_rated", "callee": "info", "is_member_call": true, "source_file": "D:\\film ele\u015ftirmen\\backend\\movie_pool_expander.py", "source_location": "L172"}, {"caller_nid": "backend_movie_pool_expander_expand_top_rated", "callee": "append", "is_member_call": true, "source_file": "D:\\film ele\u015ftirmen\\backend\\movie_pool_expander.py", "source_location": "L174"}, {"caller_nid": "backend_movie_pool_expander_expand_top_rated", "callee": "sleep", "is_member_call": true, "source_file": "D:\\film ele\u015ftirmen\\backend\\movie_pool_expander.py", "source_location": "L175"}, {"caller_nid": "backend_movie_pool_expander_expand_top_rated", "callee": "info", "is_member_call": true, "source_file": "D:\\film ele\u015ftirmen\\backend\\movie_pool_expander.py", "source_location": "L176"}, {"caller_nid": "backend_movie_pool_expander_expand_by_year", "callee": "range", "is_member_call": false, "source_file": "D:\\film ele\u015ftirmen\\backend\\movie_pool_expander.py", "source_location": "L192"}, {"caller_nid": "backend_movie_pool_expander_expand_by_year", "callee": "info", "is_member_call": true, "source_file": "D:\\film ele\u015ftirmen\\backend\\movie_pool_expander.py", "source_location": "L196"}, {"caller_nid": "backend_movie_pool_expander_expand_by_year", "callee": "sleep", "is_member_call": true, "source_file": "D:\\film ele\u015ftirmen\\backend\\movie_pool_expander.py", "source_location": "L197"}, {"caller_nid": "backend_movie_pool_expander_expand_by_year", "callee": "append", "is_member_call": true, "source_file": "D:\\film ele\u015ftirmen\\backend\\movie_pool_expander.py", "source_location": "L199"}, {"caller_nid": "backend_movie_pool_expander_expand_by_year", "callee": "info", "is_member_call": true, "source_file": "D:\\film ele\u015ftirmen\\backend\\movie_pool_expander.py", "source_location": "L200"}, {"caller_nid": "backend_movie_pool_expander_expand_by_genre", "callee": "range", "is_member_call": false, "source_file": "D:\\film ele\u015ftirmen\\backend\\movie_pool_expander.py", "source_location": "L215"}, {"caller_nid": "backend_movie_pool_expander_expand_by_genre", "callee": "sleep", "is_member_call": true, "source_file": "D:\\film ele\u015ftirmen\\backend\\movie_pool_expander.py", "source_location": "L218"}, {"caller_nid": "backend_movie_pool_expander_expand_by_genre", "callee": "append", "is_member_call": true, "source_file": "D:\\film ele\u015ftirmen\\backend\\movie_pool_expander.py", "source_location": "L220"}, {"caller_nid": "backend_movie_pool_expander_expand_by_genre", "callee": "info", "is_member_call": true, "source_file": "D:\\film ele\u015ftirmen\\backend\\movie_pool_expander.py", "source_location": "L221"}, {"caller_nid": "backend_movie_pool_expander_expand_by_language", "callee": "range", "is_member_call": false, "source_file": "D:\\film ele\u015ftirmen\\backend\\movie_pool_expander.py", "source_location": "L242"}, {"caller_nid": "backend_movie_pool_expander_expand_by_language", "callee": "sleep", "is_member_call": true, "source_file": "D:\\film ele\u015ftirmen\\backend\\movie_pool_expander.py", "source_location": "L245"}, {"caller_nid": "backend_movie_pool_expander_expand_by_language", "callee": "append", "is_member_call": true, "source_file": "D:\\film ele\u015ftirmen\\backend\\movie_pool_expander.py", "source_location": "L247"}, {"caller_nid": "backend_movie_pool_expander_expand_by_language", "callee": "info", "is_member_call": true, "source_file": "D:\\film ele\u015ftirmen\\backend\\movie_pool_expander.py", "source_location": "L248"}, {"caller_nid": "backend_movie_pool_expander_expand_similar_and_recs", "callee": "get_all_repository_movies_by_mood", "is_member_call": true, "source_file": "D:\\film ele\u015ftirmen\\backend\\movie_pool_expander.py", "source_location": "L256"}, {"caller_nid": "backend_movie_pool_expander_expand_similar_and_recs", "callee": "shuffle", "is_member_call": true, "source_file": "D:\\film ele\u015ftirmen\\backend\\movie_pool_expander.py", "source_location": "L257"}, {"caller_nid": "backend_movie_pool_expander_expand_similar_and_recs", "callee": "get", "is_member_call": true, "source_file": "D:\\film ele\u015ftirmen\\backend\\movie_pool_expander.py", "source_location": "L261"}, {"caller_nid": "backend_movie_pool_expander_expand_similar_and_recs", "callee": "AsyncClient", "is_member_call": true, "source_file": "D:\\film ele\u015ftirmen\\backend\\movie_pool_expander.py", "source_location": "L267"}, {"caller_nid": "backend_movie_pool_expander_expand_similar_and_recs", "callee": "get", "is_member_call": true, "source_file": "D:\\film ele\u015ftirmen\\backend\\movie_pool_expander.py", "source_location": "L268"}, {"caller_nid": "backend_movie_pool_expander_expand_similar_and_recs", "callee": "get", "is_member_call": true, "source_file": "D:\\film ele\u015ftirmen\\backend\\movie_pool_expander.py", "source_location": "L270"}, {"caller_nid": "backend_movie_pool_expander_expand_similar_and_recs", "callee": "json", "is_member_call": true, "source_file": "D:\\film ele\u015ftirmen\\backend\\movie_pool_expander.py", "source_location": "L270"}, {"caller_nid": "backend_movie_pool_expander_expand_similar_and_recs", "callee": "_format_movie", "is_member_call": true, "source_file": "D:\\film ele\u015ftirmen\\backend\\movie_pool_expander.py", "source_location": "L271"}, {"caller_nid": "backend_movie_pool_expander_expand_similar_and_recs", "callee": "sleep", "is_member_call": true, "source_file": "D:\\film ele\u015ftirmen\\backend\\movie_pool_expander.py", "source_location": "L275"}, {"caller_nid": "backend_movie_pool_expander_expand_similar_and_recs", "callee": "append", "is_member_call": true, "source_file": "D:\\film ele\u015ftirmen\\backend\\movie_pool_expander.py", "source_location": "L277"}, {"caller_nid": "backend_movie_pool_expander_expand_similar_and_recs", "callee": "info", "is_member_call": true, "source_file": "D:\\film ele\u015ftirmen\\backend\\movie_pool_expander.py", "source_location": "L278"}, {"caller_nid": "backend_movie_pool_expander_expand_mood_pool", "callee": "info", "is_member_call": true, "source_file": "D:\\film ele\u015ftirmen\\backend\\movie_pool_expander.py", "source_location": "L289"}, {"caller_nid": "backend_movie_pool_expander_expand_mood_pool", "callee": "info", "is_member_call": true, "source_file": "D:\\film ele\u015ftirmen\\backend\\movie_pool_expander.py", "source_location": "L298"}, {"caller_nid": "backend_movie_pool_expander_expand_all_moods", "callee": "items", "is_member_call": true, "source_file": "D:\\film ele\u015ftirmen\\backend\\movie_pool_expander.py", "source_location": "L321"}, {"caller_nid": "backend_movie_pool_expander_expand_all_moods", "callee": "get", "is_member_call": true, "source_file": "D:\\film ele\u015ftirmen\\backend\\movie_pool_expander.py", "source_location": "L321"}, {"caller_nid": "backend_movie_pool_expander_expand_all_moods", "callee": "get", "is_member_call": true, "source_file": "D:\\film ele\u015ftirmen\\backend\\movie_pool_expander.py", "source_location": "L322"}, {"caller_nid": "backend_movie_pool_expander_expand_all_moods", "callee": "extend", "is_member_call": true, "source_file": "D:\\film ele\u015ftirmen\\backend\\movie_pool_expander.py", "source_location": "L323"}, {"caller_nid": "backend_movie_pool_expander_expand_all_moods", "callee": "get", "is_member_call": true, "source_file": "D:\\film ele\u015ftirmen\\backend\\movie_pool_expander.py", "source_location": "L323"}, {"caller_nid": "backend_movie_pool_expander_expand_all_moods", "callee": "append", "is_member_call": true, "source_file": "D:\\film ele\u015ftirmen\\backend\\movie_pool_expander.py", "source_location": "L325"}]}